seven23lib/__init__.py
seven23lib/seven23.py
seven23lib/model/__init__.py
seven23lib/model/account.py
seven23lib/model/category.py
seven23lib/model/currency.py
seven23lib/model/operation.py
seven23lib-0.0.1.dist-info/DESCRIPTION.rst
seven23lib-0.0.1.dist-info/METADATA
seven23lib-0.0.1.dist-info/RECORD
seven23lib-0.0.1.dist-info/WHEEL
seven23lib-0.0.1.dist-info/metadata.json
seven23lib-0.0.1.dist-info/top_level.txt
